AUTHORS
CHANGES
LICENSE
MANIFEST.in
README
README.rst
requirements.txt
setup.py
Feedjack.egg-info/PKG-INFO
Feedjack.egg-info/SOURCES.txt
Feedjack.egg-info/dependency_links.txt
Feedjack.egg-info/entry_points.txt
Feedjack.egg-info/not-zip-safe
Feedjack.egg-info/requires.txt
Feedjack.egg-info/top_level.txt
feedjack/__init__.py
feedjack/admin.py
feedjack/apps.py
feedjack/filters.py
feedjack/fjcache.py
feedjack/fjcloud.py
feedjack/fjlib.py
feedjack/fjupdate.py
feedjack/models.py
feedjack/urls.py
feedjack/utils.py
feedjack/views.py
feedjack/fixtures/migration_data_0005.json
feedjack/fixtures/migration_data_0014.json
feedjack/locale/de/LC_MESSAGES/django.mo
feedjack/locale/de/LC_MESSAGES/django.po
feedjack/locale/en/LC_MESSAGES/django.mo
feedjack/locale/en/LC_MESSAGES/django.po
feedjack/locale/es/LC_MESSAGES/django.mo
feedjack/locale/es/LC_MESSAGES/django.po
feedjack/locale/sr/LC_MESSAGES/django.mo
feedjack/locale/sr/LC_MESSAGES/django.po
feedjack/management/__init__.py
feedjack/management/commands/__init__.py
feedjack/management/commands/feedjack_add_feed.py
feedjack/management/commands/feedjack_purge.py
feedjack/management/commands/feedjack_status.py
feedjack/management/commands/feedjack_update.py
feedjack/migrations/0001_initial.py
feedjack/migrations/0002_auto_20150203_0401.py
feedjack/migrations/0003_auto_20150203_0425.py
feedjack/migrations/0004_auto_20150204_1531.py
feedjack/migrations/0005_initial_data_migration.py
feedjack/migrations/0006_auto_20150207_1955.py
feedjack/migrations/0007_auto_20150207_2007.py
feedjack/migrations/0008_auto_20150207_2112.py
feedjack/migrations/0009_auto_20150207_2251.py
feedjack/migrations/0010_auto_20150207_2304.py
feedjack/migrations/0011_auto_20150208_0053.py
feedjack/migrations/0012_postprocessortag_tag.py
feedjack/migrations/0013_auto_20150208_0138.py
feedjack/migrations/0014_add_postproc_base_example.py
feedjack/migrations/0015_auto_20150209_0236.py
feedjack/migrations/__init__.py
feedjack/static/feedjack/jquery.js
feedjack/static/feedjack/bootstrap/default.css
feedjack/static/feedjack/bootstrap/fold.bootstrap.coffee
feedjack/static/feedjack/bootstrap/fold.bootstrap.js
feedjack/static/feedjack/bootstrap/jquery.js
