Metadata-Version: 1.1
Name: Feedjack
Version: 15.5.0
Summary: Multisite Feed Agregator (Planet) or personal feed reader
Home-page: https://github.com/mk-fg/feedjack
Author: Gustavo Picón, Mike Kazantsev
Author-email: mk.fraggod@gmail.com
License: BSD
Keywords: feed,aggregator,reader,planet,syndication,subscribe,news,web,rss,atom,rdf,opml,django,feedparser
Platform: UNKNOWN
Classifier: Development Status :: 5 - Production/Stable
Classifier: Environment :: Console
Classifier: Environment :: Web Environment
Classifier: Framework :: Django
Classifier: Intended Audience :: End Users/Desktop
Classifier: Intended Audience :: Information Technology
Classifier: License :: OSI Approved :: BSD License
Classifier: Natural Language :: English
Classifier: Operating System :: POSIX
Classifier: Operating System :: Unix
Classifier: Programming Language :: Python
Classifier: Programming Language :: Python :: 2.7
Classifier: Programming Language :: Python :: 2 :: Only
Classifier: Topic :: Internet
Classifier: Topic :: Internet :: WWW/HTTP :: Dynamic Content
Classifier: Topic :: Internet :: WWW/HTTP :: WSGI :: Application
Classifier: Topic :: Software Development :: Libraries :: Python Modules
